setup.py
atlasofsmoothspaces/__init__.py
atlasofsmoothspaces/main.py
atlasofsmoothspaces.egg-info/PKG-INFO
atlasofsmoothspaces.egg-info/SOURCES.txt
atlasofsmoothspaces.egg-info/dependency_links.txt
atlasofsmoothspaces.egg-info/top_level.txt