Metadata-Version: 2.1
Name: atlasofsmoothspaces
Version: 1.0.6
Summary: Calculating Smoothness from Input Stream
Home-page: UNKNOWN
Author: Leonhard horstmeyer
Author-email: <leonhard.horstmeyer@gmail.com>
License: UNKNOWN
Keywords: smoothness,midi
Platform: UNKNOWN
Classifier: Programming Language :: Python :: 3
Classifier: Operating System :: POSIX :: Linux
